Metadata-Version: 1.1
Name: SoccerPredict
Version: 0.0.2
Summary: A python package for soccer prediction
Home-page: https://github.com/Taiwo2020/SoccerPredictor
Author: Taiwo Gabriel
Author-email: omomuletaiwo@gmail.com
License: MIT
Platform: UNKNOWN
Classifier: Development Status :: 5 - Production/Stable
Classifier: Intended Audience :: Other Audience
Classifier: Operating System :: Microsoft :: Windows 
Classifier: Operating System :: Unix
Classifier: Operating System :: MacOS :: MacOS X
Classifier: License :: OSI Approved :: MIT License
Classifier: Programming Language :: Python :: 3.8
Classifier: Programming Language :: Python :: 3.7
Classifier: Programming Language :: Python :: 3.6
Classifier: Programming Language :: Python :: 3
